LICENSE
MANIFEST.in
README.md
_ruamel_yaml.h
_ruamel_yaml_clibz.c
_ruamel_yaml_clibz.pxd
_ruamel_yaml_clibz.pyx
api.c
config.h
dumper.c
emitter.c
loader.c
parser.c
reader.c
scanner.c
setup.py
writer.c
yaml.h
yaml_private.h
ruamel.yaml.clibz.egg-info/PKG-INFO
ruamel.yaml.clibz.egg-info/SOURCES.txt
ruamel.yaml.clibz.egg-info/dependency_links.txt
ruamel.yaml.clibz.egg-info/top_level.txt