Metadata-Version: 2.4
Name: ruamel.yaml.clibz
Version: 0.3.3
Summary: C version of reader, parser and emitter for ruamel.yaml, compiled with Zig, derived from libyaml
Author: Anthon van der Neut
Author-email: a.van.der.neut@ruamel.eu
License: MIT
Project-URL: Home, https://sourceforge.net/p/ruamel-yaml-clibz/
Project-URL: Source, https://sourceforge.net/p/ruamel-yaml-clibz/code/ci/default/tree/
Project-URL: Tracker, https://sourceforge.net/p/ruamel-yaml-clibz/tickets/
Project-URL: Documentation, https://yaml.dev/doc/ruamel.yaml.clibz
Requires-Python: >=3.9
License-File: LICENSE
Dynamic: author
Dynamic: author-email
Dynamic: description
Dynamic: description-content-type
Dynamic: license
Dynamic: license-file
Dynamic: project-url
Dynamic: requires-python
Dynamic: summary
